pytest_filter_case.py
pytest_filter_case-1.3.2.dist-info/METADATA
pytest_filter_case-1.3.2.dist-info/WHEEL
pytest_filter_case-1.3.2.dist-info/entry_points.txt
pytest_filter_case-1.3.2.dist-info/top_level.txt
pytest_filter_case-1.3.2.dist-info/RECORD
