Metadata-Version: 2.1
Name: pytest-filter-case
Version: 1.3.2
Summary: run test cases filter by mark
Home-page: https://github.com/Jason916/pytest_filter_case
Author: Jason916
Author-email: Jason1989Xu@gmail.com
License: UNKNOWN
Platform: UNKNOWN
Classifier: Programming Language :: Python
Classifier: Framework :: Pytest
Classifier: Topic :: Software Development :: Testing
